README.md
setup.cfg
setup.py
meow_base/__init__.py
meow_base/version.py
meow_base.egg-info/PKG-INFO
meow_base.egg-info/SOURCES.txt
meow_base.egg-info/dependency_links.txt
meow_base.egg-info/requires.txt
meow_base.egg-info/top_level.txt
meow_base/conductors/__init__.py
meow_base/conductors/local_bash_conductor.py
meow_base/conductors/local_python_conductor.py
meow_base/core/__init__.py
meow_base/core/base_conductor.py
meow_base/core/base_handler.py
meow_base/core/base_monitor.py
meow_base/core/base_pattern.py
meow_base/core/base_recipe.py
meow_base/core/meow.py
meow_base/core/rule.py
meow_base/core/runner.py
meow_base/core/vars.py
meow_base/functionality/__init__.py
meow_base/functionality/debug.py
meow_base/functionality/file_io.py
meow_base/functionality/hashing.py
meow_base/functionality/meow.py
meow_base/functionality/naming.py
meow_base/functionality/notifications.py
meow_base/functionality/parameterisation.py
meow_base/functionality/process_io.py
meow_base/functionality/requirements.py
meow_base/functionality/validation.py
meow_base/patterns/__init__.py
meow_base/patterns/file_event_pattern.py
meow_base/patterns/socket_event_pattern.py
meow_base/recipes/__init__.py
meow_base/recipes/bash_recipe.py
meow_base/recipes/jupyter_notebook_recipe.py
meow_base/recipes/python_recipe.py