Metadata-Version: 2.1
Name: meow-base
Version: 1.0.5
Summary: A base framework for MEOW based implementations of workflows
Home-page: https://github.com/PatchOfScotland/meow_base
Author: David Marchant
Author-email: d.marchant@ed-alumni.net
License: MIT
Platform: UNKNOWN
Classifier: Programming Language :: Python :: 3
Classifier: License :: OSI Approved :: GNU General Public License (GPL)
Classifier: Operating System :: OS Independent
